flake8_filename/__init__.py
flake8_filename/rules.py
flake8_filename-1.0.0.dist-info/METADATA
flake8_filename-1.0.0.dist-info/RECORD
flake8_filename-1.0.0.dist-info/WHEEL
flake8_filename-1.0.0.dist-info/entry_points.txt
flake8_filename-1.0.0.dist-info/top_level.txt
